niet/__init__.py
niet/__main__.py
niet/output.py
niet/url.py
niet-3.2.0.dist-info/METADATA
niet-3.2.0.dist-info/WHEEL
niet-3.2.0.dist-info/entry_points.txt
niet-3.2.0.dist-info/licenses/AUTHORS
niet-3.2.0.dist-info/licenses/LICENSE
niet-3.2.0.dist-info/RECORD
