Metadata-Version: 2.1
Name: niet
Version: 3.2.0
Summary: A command-line tool to work with YAML, JSON, and TOML files.
Author-email: Hervé Beraud <herveberaud.pro@gmail.com>
License: MIT
License-File: AUTHORS
License-File: LICENSE
Classifier: Environment :: Console
Classifier: Intended Audience :: Developers
Classifier: License :: OSI Approved :: MIT License
Classifier: Operating System :: OS Independent
Classifier: Programming Language :: Python
Classifier: Programming Language :: Python :: 3
Classifier: Programming Language :: Python :: 3.9
Classifier: Programming Language :: Python :: 3.10
Classifier: Programming Language :: Python :: 3.11
Classifier: Topic :: Software Development
Classifier: Topic :: Utilities
Requires-Python: >=3.9
Requires-Dist: jmespath>=0.9.4
Requires-Dist: pytoml
Requires-Dist: pyyaml>=5.1
Provides-Extra: dev
Requires-Dist: black; extra == 'dev'
Requires-Dist: build; extra == 'dev'
Requires-Dist: commitizen; extra == 'dev'
Requires-Dist: isort; extra == 'dev'
Requires-Dist: pip-tools; extra == 'dev'
Requires-Dist: pre-commit; extra == 'dev'
Requires-Dist: twine; extra == 'dev'
